emailtools/__init__.py
emailtools/emailtools.py
tl_emailtools-1.1.1.dist-info/licenses/LICENSE
tl_emailtools-1.1.1.dist-info/METADATA
tl_emailtools-1.1.1.dist-info/WHEEL
tl_emailtools-1.1.1.dist-info/top_level.txt
tl_emailtools-1.1.1.dist-info/RECORD
