Metadata-Version: 2.4
Name: tl-emailtools
Version: 1.1.1
Summary: A email-tool package simplified sending email.
Author-email: TongLeen <Tong.Leen@outlook.com>
Project-URL: Homepage, https://github.com/TongLeen/emailtools-python3
Project-URL: Repository, https://github.com/TongLeen/emailtools-python3.git
Keywords: email
Requires-Python: >=3.12
License-File: LICENSE
Dynamic: license-file
